{
  "name": "upsolve-br/packages",
  "version": "1.0.0",
  "description": "Repositório privado de pacotes PHP da UpSolve Technologies",
  "homepage": "https://packages.upsolve.com.br",
  "repositories": [
    { "type": "vcs", "url": "https://github.com/upsolve-br/contracts" },
    { "type": "vcs", "url": "https://github.com/upsolve-br/user-management" },
    { "type": "vcs", "url": "https://github.com/upsolve-br/filament-language-switch" },
    { "type": "vcs", "url": "https://github.com/upsolve-br/filament-shield" }
  ],
  "require-all": true,
  "archive": {
    "directory": "dist",
    "format": "zip",
    "skip-dev": true
  },
  "output-dir": "/var/satis/output",
  "output-html": true
}